dmmp/__init__.py
dmmp/__main__.py
dmmp/args.py
dmmp/exceptions.py
dmmp/mapper.py
dmmp-0.3.1.dist-info/METADATA
dmmp-0.3.1.dist-info/WHEEL
dmmp-0.3.1.dist-info/licenses/LICENSE
dmmp-0.3.1.dist-info/RECORD
