Metadata-Version: 2.4
Name: dmmp
Version: 0.3.1
Summary: Directory metadata mapper protocol for documenting directories
Project-URL: Homepage, https://github.com/GabrielvMarinho/dmmp
Project-URL: Repository, https://github.com/GabrielvMarinho/dmmp
Project-URL: Issues, https://github.com/GabrielvMarinho/dmmp/issues
Author-email: Gabriel Volles Marinho <gabrielvmarinho1711@gmail.com>
License-Expression: MIT
License-File: LICENSE
Classifier: Programming Language :: Python :: 3
Requires-Python: >=3.9
Requires-Dist: colorama>=0.4.6
Requires-Dist: python-dotenv>=1.0.0
Requires-Dist: tomli-w==1.2.0
Requires-Dist: tqdm>=4.60.0
